gtts/__init__.py
gtts/accents.py
gtts/cli.py
gtts/lang.py
gtts/langs.py
gtts/tts.py
gtts/utils.py
gtts/version.py
gtts/tests/__init__.py
gtts/tests/test_cli.py
gtts/tests/test_lang.py
gtts/tests/test_tts.py
gtts/tests/test_utils.py
gtts/tests/input_files/test_cli_test_ascii.txt
gtts/tests/input_files/test_cli_test_utf8.txt
gtts/tokenizer/__init__.py
gtts/tokenizer/core.py
gtts/tokenizer/pre_processors.py
gtts/tokenizer/symbols.py
gtts/tokenizer/tokenizer_cases.py
gtts/tokenizer/tests/test_core.py
gtts/tokenizer/tests/test_pre_processors.py
gtts/tokenizer/tests/test_tokenizer_cases.py
gTTS-2.5.3.dist-info/LICENSE
gTTS-2.5.3.dist-info/METADATA
gTTS-2.5.3.dist-info/WHEEL
gTTS-2.5.3.dist-info/entry_points.txt
gTTS-2.5.3.dist-info/top_level.txt
gTTS-2.5.3.dist-info/RECORD
