Metadata-Version: 2.1
Name: gTTS
Version: 2.5.3
Summary: gTTS (Google Text-to-Speech), a Python library and CLI tool to interface with Google Translate text-to-speech API
Author-email: Pierre Nicolas Durette <pndurette@gmail.com>
License: MIT
Project-URL: homepage, https://github.com/pndurette/gTTS
Project-URL: documentation, https://gtts.readthedocs.io
Project-URL: repository, https://github.com/pndurette/gTTS
Project-URL: changelog, https://github.com/pndurette/gTTS/blob/main/CHANGELOG.md
Keywords: gtts,text to speech,Google Translate,TTS
Classifier: Environment :: Console
Classifier: Intended Audience :: Developers
Classifier: License :: OSI Approved :: MIT License
Classifier: Operating System :: MacOS
Classifier: Operating System :: Unix
Classifier: Operating System :: POSIX
Classifier: Operating System :: POSIX :: Linux
Classifier: Operating System :: Microsoft :: Windows
Classifier: Programming Language :: Python :: 3.8
Classifier: Programming Language :: Python :: 3.9
Classifier: Programming Language :: Python :: 3.10
Classifier: Programming Language :: Python :: 3.11
Classifier: Programming Language :: Python :: 3.12
Classifier: Topic :: Software Development :: Libraries
Classifier: Topic :: Multimedia :: Sound/Audio :: Speech
Requires-Python: >=3.7
License-File: LICENSE
Requires-Dist: requests<3,>=2.27
Requires-Dist: click<8.2,>=7.1
Provides-Extra: tests
Requires-Dist: pytest<8.4.0,>=7.1.3; extra == "tests"
Requires-Dist: pytest-cov; extra == "tests"
Requires-Dist: testfixtures; extra == "tests"
Provides-Extra: docs
Requires-Dist: sphinx; extra == "docs"
Requires-Dist: sphinx-autobuild; extra == "docs"
Requires-Dist: sphinx_rtd_theme; extra == "docs"
Requires-Dist: sphinx-click; extra == "docs"
Requires-Dist: sphinx-mdinclude; extra == "docs"
